{
  "id": "case-005",
  "title": "OKR Builder",
  "category": "Estratégia",
  "description": "Case da criação de um sistema multiagentes para criação de OKRs. ",
  "timeReduction": "11%",
  "qualityImprovement": "11%",
  "iconName": "Lightbulb",
  "color": "bg-red-100",
  "author": "Danilo Custódio",
  "summary": "Teste 1",
  "promptExample": "Teste 1",
  "result": "Teste 1",
  "videoLength": "",
  "videoViews": "",
  "productName": "OKR Builder",
  "createdAt": "2025-03-16T19:17:27.282Z",
  "updatedAt": "2025-04-09T04:02:10.782Z",
  "version": 1,
  "highlights": [
    ""
  ],
  "tabs": {
    "overview": {
      "description": ""
    },
    "video": {
      "url": "https://youtu.be/d6q6H0WVx_E",
      "thumbnail": "",
      "highlights": [
        ""
      ],
      "resources": []
    },
    "process": {
      "steps": [
        ""
      ]
    },
    "results": {
      "before": [
        ""
      ],
      "after": [
        ""
      ]
    },
    "lessons": {
      "whatWorked": [
        ""
      ],
      "improvementAreas": [
        ""
      ],
      "tips": [
        ""
      ]
    }
  }
}